zombie_squirrel/__init__.py
zombie_squirrel/acorns.py
zombie_squirrel/squirrels.py
zombie_squirrel/sync.py
zombie_squirrel/utils.py
zombie_squirrel-0.7.4.dist-info/licenses/LICENSE
zombie_squirrel-0.7.4.dist-info/METADATA
zombie_squirrel-0.7.4.dist-info/WHEEL
zombie_squirrel-0.7.4.dist-info/top_level.txt
zombie_squirrel-0.7.4.dist-info/RECORD
