Metadata-Version: 2.4
Name: zombie-squirrel
Version: 0.7.4
Summary: Generated from aind-library-template
Author: Allen Institute for Neural Dynamics
License: MIT
Classifier: Programming Language :: Python :: 3
Requires-Python: >=3.10
License-File: LICENSE
Requires-Dist: duckdb
Requires-Dist: fastparquet<2025
Requires-Dist: boto3
Requires-Dist: pandas
Requires-Dist: aind-data-access-api[docdb]
Dynamic: license-file
